{
  "_id": "AfodViceLujo0001",
  "name": "Lujo",
  "type": "vice",
  "img": "icons/commodities/treasure/goblet-worn-gold.webp",
  "system": {
    "description": "<p>Exhibiciones costosas y/u ostentosas de opulencia.</p><p>Detalla tu vicio específico e indica el nombre y ubicación de tu proveedor de vicio (joyero, modista, restaurante de lujo, etc.).</p>"
  },
  "effects": [],
  "folder": "E5e5a30VY1ilC3gD",
  "sort": 300000,
  "ownership": {
    "default": 0
  },
  "flags": {},
  "_stats": {
    "compendiumSource": null,
    "duplicateSource": null,
    "exportSource": null,
    "coreVersion": "13.351",
    "systemId": "a-fistful-of-darkness",
    "systemVersion": "0.1.0",
    "createdTime": 1774374325584,
    "modifiedTime": 1774374325584,
    "lastModifiedBy": null
  },
  "_key": "!items!AfodViceLujo0001"
}